cns_algos/__init__.py
cns_algos/aes.py
cns_algos/cns_algos.py
cns_algos-0.0.1.dist-info/LICENSE
cns_algos-0.0.1.dist-info/METADATA
cns_algos-0.0.1.dist-info/WHEEL
cns_algos-0.0.1.dist-info/top_level.txt
cns_algos-0.0.1.dist-info/RECORD
