Metadata-Version: 2.1
Name: cns-algos
Version: 0.0.1
Summary: A package with all algorithms used in Cryptography. Detailed list in README.
Home-page: https://github.com/charlescsr/cns_algos
Author: Charles Samuel R
Author-email: rcharles.samuel99@gmail.com
License: UNKNOWN
Platform: UNKNOWN
Classifier: Programming Language :: Python :: 3
Classifier: License :: OSI Approved :: MIT License
Classifier: Operating System :: OS Independent
Requires-Python: >=3.6
Requires-Dist: numpy
Requires-Dist: sympy
Requires-Dist: des
Requires-Dist: pycryptodome
